{
  "version": 2,
  "extractor": "pdffigures2",
  "figures": [
    {
      "url": "assets/figures/arxiv/2604.06631v1/fig-001.webp",
      "caption": "Table 1. Experimental results(%) under label skew settings and real-world settings.",
      "page": 6,
      "index": 1,
      "width": 1026,
      "height": 339
    },
    {
      "url": "assets/figures/arxiv/2604.06631v1/fig-002.webp",
      "caption": "Table 2. Experimental results(%) under feature shift Settings.",
      "page": 6,
      "index": 2,
      "width": 922,
      "height": 332
    },
    {
      "url": "assets/figures/arxiv/2604.06631v1/fig-003.webp",
      "caption": "Figure 5. Performance comparison under varying pruning rates on CIFAR-10. SubFLOT maintains strong accuracy and stability even at high sparsity levels.",
      "page": 15,
      "index": 3,
      "width": 912,
      "height": 360
    },
    {
      "url": "assets/figures/arxiv/2604.06631v1/fig-004.webp",
      "caption": "Figure 6. Qualitative comparison of activation maps generated by SubFLOT and baseline methods. SubFLOT successfully preserves the task-relevant attention patterns of the local model (column 2), demonstrating effective feature alignment. In contrast, fixed-position pruning fails to adapt to local data, while magnitude-based and random pruning exhibit fragmented or noisy attention, indicating a misalignment with client-specific features.",
      "page": 15,
      "index": 4,
      "width": 1036,
      "height": 551
    },
    {
      "url": "assets/figures/arxiv/2604.06631v1/fig-005.webp",
      "caption": "Table 4. Impact of Heterogeneity Degree.",
      "page": 7,
      "index": 5,
      "width": 487,
      "height": 294
    },
    {
      "url": "assets/figures/arxiv/2604.06631v1/fig-006.webp",
      "caption": "Table 3. Impact of Number of Clients.",
      "page": 7,
      "index": 6,
      "width": 487,
      "height": 301
    },
    {
      "url": "assets/figures/arxiv/2604.06631v1/fig-007.webp",
      "caption": "Figure 2. Feature Visualization of our SubFLOT.",
      "page": 7,
      "index": 7,
      "width": 1036,
      "height": 181
    },
    {
      "url": "assets/figures/arxiv/2604.06631v1/fig-008.webp",
      "caption": "Figure 4. Hyperparameter sensitivity analysis of SubFLOT on multiple datasets and heterogeneity settings. The results show that α mainly controls the personalization–stability trade-off, while λ primarily regulates pruning-induced parametric divergence.",
      "page": 14,
      "index": 8,
      "width": 1027,
      "height": 304
    },
    {
      "url": "assets/figures/arxiv/2604.06631v1/fig-009.webp",
      "caption": "Figure 1. An overview of the proposed SubFLOT framework. On the server, Optimal Transport-enhanced Pruning (OTP) leverages historical models to generate personalized, heterogeneous submodels for clients. Clients then train these submodels locally, guided by Scaling-based Adaptive Regularization (SAR). Finally, the server utilizes the repurposed OT-enhanced Aggregation (OTA) module to align and aggregate the updated submodels, improving global model convergence.",
      "page": 3,
      "index": 9,
      "width": 1036,
      "height": 495
    },
    {
      "url": "assets/figures/arxiv/2604.06631v1/fig-010.webp",
      "caption": "Figure 3. Comparison of total wall-clock time required to complete 200 communication rounds (left) and to reach 80% test accuracy (right) on CIFAR-10. Although OT introduces additional server-side computation, SubFLOT achieves a superior time-to-accuracy trade-off due to faster convergence.",
      "page": 13,
      "index": 10,
      "width": 1029,
      "height": 333
    },
    {
      "url": "assets/figures/arxiv/2604.06631v1/fig-011.webp",
      "caption": "Table 5. Impact of Model Sparsity.",
      "page": 8,
      "index": 11,
      "width": 422,
      "height": 302
    },
    {
      "url": "assets/figures/arxiv/2604.06631v1/fig-012.webp",
      "caption": "Table 9. Dataset Specifications. Our evaluation covers diverse data modalities and includes multi-domain benchmarks (Digit-5, PACS) to rigorously assess model generalization and robustness against feature distribution shifts.",
      "page": 12,
      "index": 12,
      "width": 875,
      "height": 273
    }
  ]
}